{
  "plant": "Kirkwood Tops",
  "last_updated": "2026-03-21 19:45 SAST",
  "date": "2026-03-21",
  "total_kwh": 50.6,
  "last_hour": 19,
  "status": "ok",
  "alerts": {
    "offline": false,
    "pace_low": false,
    "total_low": false
  },
  "today": {
    "hourly_pv": [
      0.0,
      0.0,
      0.0,
      0.0,
      0.0,
      0.0,
      0.0,
      1.1,
      0.0,
      5.8,
      6.6,
      6.9,
      7.5,
      6.9,
      0.0,
      13.6,
      1.6,
      0.6,
      0.0,
      0.0,
      0.0,
      0.0,
      0.0,
      0.0
    ],
    "irradiation": [
      0,
      0,
      0,
      0,
      0,
      0,
      0,
      15.0,
      122.0,
      267.0,
      387.0,
      532.0,
      602.0,
      616.0,
      452.0,
      439.0,
      443.0,
      268.0,
      128.0,
      8.0,
      0,
      0,
      0,
      0
    ]
  },
  "hourly_pv": [
    0.0,
    0.0,
    0.0,
    0.0,
    0.0,
    0.0,
    0.0,
    1.1,
    0.0,
    5.8,
    6.6,
    6.9,
    7.5,
    6.9,
    0.0,
    13.6,
    1.6,
    0.6,
    0.0,
    0.0,
    0.0,
    0.0,
    0.0,
    0.0
  ],
  "irradiation": [
    0,
    0,
    0,
    0,
    0,
    0,
    0,
    15.0,
    122.0,
    267.0,
    387.0,
    532.0,
    602.0,
    616.0,
    452.0,
    439.0,
    443.0,
    268.0,
    128.0,
    8.0,
    0,
    0,
    0,
    0
  ],
  "stats_30day": {
    "hourly_avg": [
      0.0,
      0.0,
      0.0,
      0.0,
      0.0,
      0.0,
      0.0,
      0.55,
      0.0,
      2.9,
      3.3,
      3.45,
      3.75,
      3.45,
      0.0,
      6.8,
      0.8,
      0.3,
      0.0,
      0.0,
      0.0,
      0.0,
      0.0,
      0.0
    ],
    "hourly_min": [
      0.0,
      0.0,
      0.0,
      0.0,
      0.0,
      0.0,
      0.0,
      0.0,
      0.0,
      0.0,
      0.0,
      0.0,
      0.0,
      0.0,
      0.0,
      0.0,
      0.0,
      0.0,
      0.0,
      0.0,
      0.0,
      0.0,
      0.0,
      0.0
    ],
    "hourly_max": [
      0.0,
      0.0,
      0.0,
      0.0,
      0.0,
      0.0,
      0.0,
      1.1,
      0.0,
      5.8,
      6.6,
      6.9,
      7.5,
      6.9,
      0.0,
      13.6,
      1.6,
      0.6,
      0.0,
      0.0,
      0.0,
      0.0,
      0.0,
      0.0
    ],
    "hourly_p10": [
      0.0,
      0.0,
      0.0,
      0.0,
      0.0,
      0.0,
      0.0,
      0.11,
      0.0,
      0.58,
      0.66,
      0.69,
      0.75,
      0.69,
      0.0,
      1.36,
      0.16,
      0.06,
      0.0,
      0.0,
      0.0,
      0.0,
      0.0,
      0.0
    ],
    "hourly_p25": [
      0.0,
      0.0,
      0.0,
      0.0,
      0.0,
      0.0,
      0.0,
      0.28,
      0.0,
      1.45,
      1.65,
      1.73,
      1.88,
      1.73,
      0.0,
      3.4,
      0.4,
      0.15,
      0.0,
      0.0,
      0.0,
      0.0,
      0.0,
      0.0
    ],
    "hourly_p75": [
      0.0,
      0.0,
      0.0,
      0.0,
      0.0,
      0.0,
      0.0,
      0.83,
      0.0,
      4.35,
      4.95,
      5.18,
      5.62,
      5.18,
      0.0,
      10.2,
      1.2,
      0.45,
      0.0,
      0.0,
      0.0,
      0.0,
      0.0,
      0.0
    ],
    "hourly_p90": [
      0.0,
      0.0,
      0.0,
      0.0,
      0.0,
      0.0,
      0.0,
      0.99,
      0.0,
      5.22,
      5.94,
      6.21,
      6.75,
      6.21,
      0.0,
      12.24,
      1.44,
      0.54,
      0.0,
      0.0,
      0.0,
      0.0,
      0.0,
      0.0
    ],
    "daily_min": 50.6,
    "daily_max": 51.8,
    "daily_avg": 51.2,
    "sample_days": 2
  },
  "history": {
    "2026-03-20": {
      "total_kwh": 51.8,
      "hourly": [
        0.0,
        0.0,
        0.0,
        0.0,
        0.0,
        0.0,
        0.0,
        0.0,
        0.0,
        0.0,
        0.0,
        0.0,
        0.0,
        0.0,
        0.0,
        0.0,
        0.0,
        0.0,
        0.0,
        0.0,
        0.0,
        0.0,
        0.0,
        0.0
      ],
      "irradiation": [
        0,
        0,
        0,
        0,
        0,
        0,
        0,
        14.0,
        119.0,
        268.0,
        308.0,
        368.0,
        689.0,
        772.0,
        718.0,
        513.0,
        388.0,
        282.0,
        115.0,
        7.0,
        0,
        0,
        0,
        0
      ],
      "last_updated": "2026-03-20 23:48 SAST",
      "last_hour": 23
    },
    "2026-03-21": {
      "total_kwh": 50.6,
      "hourly": [
        0.0,
        0.0,
        0.0,
        0.0,
        0.0,
        0.0,
        0.0,
        1.1,
        0.0,
        5.8,
        6.6,
        6.9,
        7.5,
        6.9,
        0.0,
        13.6,
        1.6,
        0.6,
        0.0,
        0.0,
        0.0,
        0.0,
        0.0,
        0.0
      ],
      "irradiation": [
        0,
        0,
        0,
        0,
        0,
        0,
        0,
        15.0,
        122.0,
        267.0,
        387.0,
        532.0,
        602.0,
        616.0,
        452.0,
        439.0,
        443.0,
        268.0,
        128.0,
        8.0,
        0,
        0,
        0,
        0
      ],
      "last_updated": "2026-03-21 19:45 SAST",
      "last_hour": 19
    }
  },
  "thresholds": {
    "expected_daily_kwh": 37.0,
    "low_day_kwh": 50.6,
    "pace_threshold_pct": 0.3,
    "solar_window": {
      "sunrise": 5.92,
      "sunset": 18.08
    }
  },
  "debug": {
    "curve_fraction": 1.0,
    "expected_by_now": 37.0,
    "actual_kwh": 50.6,
    "pace_trigger": 11.1,
    "projected_total": 50.6,
    "low_day_kwh": 50.6,
    "sunrise": 5.92,
    "sunset": 18.08,
    "checks": {
      "pace_low": false,
      "total_low": false
    }
  }
}